{
  "id": "0myemo4sct",
  "context": {
    "tab": "sketchpad",
    "file": "src/sketchpads/sketchpad-1/frame-fw0ze7.tsx",
    "sketchpadId": "sketchpad-1",
    "frameId": "frame-fw0ze7",
    "sketchpadName": "Sketchpad 1",
    "frameName": "Frame 2"
  },
  "comments": [
    {
      "id": "c-d4jngz886p",
      "author": {
        "name": "Maciej Sawicki",
        "email": "saw.maciej@gmail.com"
      },
      "content": "Test asd",
      "createdAt": "2026-06-27T18:33:47.004Z"
    }
  ],
  "createdAt": "2026-06-27T18:33:47.004Z",
  "anchorFile": "src/sketchpads/sketchpad-1/frame-fw0ze7.tsx"
}